README.rst
setup.py
Templator.egg-info/PKG-INFO
Templator.egg-info/SOURCES.txt
Templator.egg-info/dependency_links.txt
Templator.egg-info/entry_points.txt
Templator.egg-info/requires.txt
Templator.egg-info/top_level.txt
templetor/__init__.py
templetor/main.py