Metadata-Version: 1.1
Name: Templator
Version: 0.0.1
Summary: Distribution
Home-page: http://www.python.org/sigs/distutils-sig/
Author: Singularity
Author-email: Singularitty@gmail.com
License: ISC
Platform: UNKNOWN
Classifier: Environment :: Console
Classifier: Intended Audience :: Developers
Classifier: Natural Language :: English
Classifier: License :: OSI Approved :: ISC License (ISCL)
Classifier: Programming Language :: Python
Classifier: Programming Language :: Python :: 2
Classifier: Programming Language :: Python :: 2.6
Classifier: Programming Language :: Python :: 2.7
